{
    "candidates": {
        "1": {
            "name": "許美智",
            "party": "民主進步黨"
        }
    },
    "data": [
        {
            "area": "大同區",
            "cunli": "大有里",
            "house_no": "1072",
            "candidates": {
                "1": 664
            },
            "count_wrong": 141,
            "count_unused": 0,
            "count_total": 1227
        },
        {
            "area": "大同區",
            "cunli": "大有里",
            "house_no": "1073",
            "candidates": {
                "1": 670
            },
            "count_wrong": 116,
            "count_unused": 0,
            "count_total": 1189
        },
        {
            "area": "大同區",
            "cunli": "大有里",
            "house_no": "1074",
            "candidates": {
                "1": 649
            },
            "count_wrong": 195,
            "count_unused": 0,
            "count_total": 1210
        }
    ]
}