{
    "candidates": {
        "1": {
            "name": "蕭有祥",
            "party": "無"
        },
        "2": {
            "name": "陳志勇",
            "party": "無"
        },
        "3": {
            "name": "陳宥彤",
            "party": "無"
        },
        "4": {
            "name": "張鵬瑜",
            "party": "無"
        },
        "5": {
            "name": "彭瑞華",
            "party": "無"
        },
        "6": {
            "name": "許萬福",
            "party": "無"
        },
        "7": {
            "name": "管慧莉",
            "party": "無"
        },
        "8": {
            "name": "王秋助",
            "party": "中國國民黨"
        },
        "9": {
            "name": "葛榮正",
            "party": "無"
        },
        "10": {
            "name": "徐裕傑",
            "party": "無"
        },
        "11": {
            "name": "傅靜如",
            "party": "無"
        }
    },
    "data": [
        {
            "area": "第1選舉區",
            "cunli": "南勢里",
            "house_no": "1864",
            "candidates": {
                "1": 184,
                "2": 159,
                "3": 136,
                "4": 1,
                "5": 8,
                "6": 20,
                "7": 20,
                "8": 106,
                "9": 13,
                "10": 8,
                "11": 5
            },
            "count_wrong": 22,
            "count_unused": 0,
            "count_total": 931
        },
        {
            "area": "第1選舉區",
            "cunli": "南勢里",
            "house_no": "1865",
            "candidates": {
                "1": 163,
                "2": 105,
                "3": 78,
                "4": 2,
                "5": 7,
                "6": 118,
                "7": 81,
                "8": 72,
                "9": 68,
                "10": 29,
                "11": 3
            },
            "count_wrong": 8,
            "count_unused": 0,
            "count_total": 938
        },
        {
            "area": "第1選舉區",
            "cunli": "天輪里",
            "house_no": "1866",
            "candidates": {
                "1": 60,
                "2": 38,
                "3": 37,
                "4": 2,
                "5": 28,
                "6": 2,
                "7": 16,
                "8": 52,
                "9": 9,
                "10": 76,
                "11": 13
            },
            "count_wrong": 8,
            "count_unused": 0,
            "count_total": 450
        },
        {
            "area": "第1選舉區",
            "cunli": "博愛里",
            "house_no": "1867",
            "candidates": {
                "1": 15,
                "2": 57,
                "3": 44,
                "4": 2,
                "5": 6,
                "6": 50,
                "7": 98,
                "8": 36,
                "9": 149,
                "10": 209,
                "11": 6
            },
            "count_wrong": 11,
            "count_unused": 0,
            "count_total": 944
        },
        {
            "area": "第1選舉區",
            "cunli": "博愛里第2選舉區",
            "house_no": "1868",
            "candidates": {
                "1": 27,
                "2": 103,
                "3": 38,
                "4": 8,
                "5": 9,
                "6": 37,
                "7": 40,
                "8": 34,
                "9": 76,
                "10": 60,
                "11": 1
            },
            "count_wrong": 10,
            "count_unused": 0,
            "count_total": 628
        },
        {
            "area": "第1選舉區",
            "cunli": "自由里",
            "house_no": "1869",
            "candidates": {
                "1": 81,
                "2": 7,
                "3": 111,
                "4": 0,
                "5": 0,
                "6": 0,
                "7": 0,
                "8": 0,
                "9": 0,
                "10": 0,
                "11": 0
            },
            "count_wrong": 9,
            "count_unused": 0,
            "count_total": 271
        },
        {
            "area": "第1選舉區",
            "cunli": "自由里",
            "house_no": "1870",
            "candidates": {
                "1": 46,
                "2": 43,
                "3": 229,
                "4": 0,
                "5": 0,
                "6": 0,
                "7": 0,
                "8": 0,
                "9": 0,
                "10": 0,
                "11": 0
            },
            "count_wrong": 23,
            "count_unused": 0,
            "count_total": 439
        },
        {
            "area": "第1選舉區",
            "cunli": "自由里",
            "house_no": "1871",
            "candidates": {
                "1": 117,
                "2": 89,
                "3": 18,
                "4": 0,
                "5": 0,
                "6": 0,
                "7": 0,
                "8": 0,
                "9": 0,
                "10": 0,
                "11": 0
            },
            "count_wrong": 9,
            "count_unused": 0,
            "count_total": 314
        },
        {
            "area": "第1選舉區",
            "cunli": "達觀里",
            "house_no": "1872",
            "candidates": {
                "1": 199,
                "2": 78,
                "3": 246,
                "4": 0,
                "5": 0,
                "6": 0,
                "7": 0,
                "8": 0,
                "9": 0,
                "10": 0,
                "11": 0
            },
            "count_wrong": 32,
            "count_unused": 0,
            "count_total": 758
        },
        {
            "area": "第1選舉區",
            "cunli": "達觀里",
            "house_no": "1873",
            "candidates": {
                "1": 60,
                "2": 14,
                "3": 170,
                "4": 0,
                "5": 0,
                "6": 0,
                "7": 0,
                "8": 0,
                "9": 0,
                "10": 0,
                "11": 0
            },
            "count_wrong": 7,
            "count_unused": 0,
            "count_total": 339
        },
        {
            "area": "第1選舉區",
            "cunli": "中坑里第3選舉區",
            "house_no": "1874",
            "candidates": {
                "1": 145,
                "2": 127,
                "3": 48,
                "4": 0,
                "5": 0,
                "6": 0,
                "7": 0,
                "8": 0,
                "9": 0,
                "10": 0,
                "11": 0
            },
            "count_wrong": 19,
            "count_unused": 0,
            "count_total": 444
        },
        {
            "area": "第1選舉區",
            "cunli": "梨山里",
            "house_no": "1875",
            "candidates": {
                "1": 61,
                "2": 49,
                "3": 43,
                "4": 65,
                "5": 0,
                "6": 0,
                "7": 0,
                "8": 0,
                "9": 0,
                "10": 0,
                "11": 0
            },
            "count_wrong": 1,
            "count_unused": 0,
            "count_total": 355
        },
        {
            "area": "第1選舉區",
            "cunli": "梨山里",
            "house_no": "1876",
            "candidates": {
                "1": 127,
                "2": 120,
                "3": 62,
                "4": 70,
                "5": 0,
                "6": 0,
                "7": 0,
                "8": 0,
                "9": 0,
                "10": 0,
                "11": 0
            },
            "count_wrong": 9,
            "count_unused": 0,
            "count_total": 740
        },
        {
            "area": "第1選舉區",
            "cunli": "梨山里",
            "house_no": "1877",
            "candidates": {
                "1": 117,
                "2": 82,
                "3": 62,
                "4": 25,
                "5": 0,
                "6": 0,
                "7": 0,
                "8": 0,
                "9": 0,
                "10": 0,
                "11": 0
            },
            "count_wrong": 9,
            "count_unused": 0,
            "count_total": 521
        },
        {
            "area": "第1選舉區",
            "cunli": "梨山里",
            "house_no": "1878",
            "candidates": {
                "1": 40,
                "2": 52,
                "3": 76,
                "4": 30,
                "5": 0,
                "6": 0,
                "7": 0,
                "8": 0,
                "9": 0,
                "10": 0,
                "11": 0
            },
            "count_wrong": 4,
            "count_unused": 0,
            "count_total": 276
        },
        {
            "area": "第1選舉區",
            "cunli": "平等里",
            "house_no": "1879",
            "candidates": {
                "1": 25,
                "2": 4,
                "3": 35,
                "4": 16,
                "5": 0,
                "6": 0,
                "7": 0,
                "8": 0,
                "9": 0,
                "10": 0,
                "11": 0
            },
            "count_wrong": 0,
            "count_unused": 0,
            "count_total": 146
        },
        {
            "area": "第1選舉區",
            "cunli": "平等里",
            "house_no": "1880",
            "candidates": {
                "1": 94,
                "2": 22,
                "3": 314,
                "4": 172,
                "5": 0,
                "6": 0,
                "7": 0,
                "8": 0,
                "9": 0,
                "10": 0,
                "11": 0
            },
            "count_wrong": 8,
            "count_unused": 0,
            "count_total": 757
        }
    ]
}