{
    "candidates": {
        "1": {
            "name": "林德松",
            "party": "無"
        }
    },
    "data": [
        {
            "area": "鹽埕區",
            "cunli": "河濱里",
            "house_no": "956",
            "candidates": {
                "1": 349
            },
            "count_wrong": 84,
            "count_unused": 0,
            "count_total": 741
        },
        {
            "area": "鹽埕區",
            "cunli": "河濱里",
            "house_no": "957",
            "candidates": {
                "1": 337
            },
            "count_wrong": 83,
            "count_unused": 0,
            "count_total": 732
        }
    ]
}