{
    "candidates": {
        "1": {
            "name": "陳廖安",
            "party": "中國國民黨"
        },
        "2": {
            "name": "吳萬德",
            "party": "無"
        },
        "3": {
            "name": "許德志",
            "party": "無"
        }
    },
    "data": [
        {
            "area": "瑞穗鄉",
            "cunli": "瑞穗村",
            "house_no": "272",
            "candidates": {
                "1": 159,
                "2": 229,
                "3": 81
            },
            "count_wrong": 9,
            "count_unused": 0,
            "count_total": 740
        },
        {
            "area": "瑞穗鄉",
            "cunli": "瑞穗村",
            "house_no": "273",
            "candidates": {
                "1": 183,
                "2": 382,
                "3": 84
            },
            "count_wrong": 12,
            "count_unused": 0,
            "count_total": 999
        },
        {
            "area": "瑞穗鄉",
            "cunli": "瑞美村",
            "house_no": "274",
            "candidates": {
                "1": 187,
                "2": 238,
                "3": 116
            },
            "count_wrong": 9,
            "count_unused": 0,
            "count_total": 853
        },
        {
            "area": "瑞穗鄉",
            "cunli": "瑞美村",
            "house_no": "275",
            "candidates": {
                "1": 211,
                "2": 269,
                "3": 129
            },
            "count_wrong": 24,
            "count_unused": 0,
            "count_total": 938
        },
        {
            "area": "瑞穗鄉",
            "cunli": "瑞良村",
            "house_no": "276",
            "candidates": {
                "1": 123,
                "2": 178,
                "3": 47
            },
            "count_wrong": 7,
            "count_unused": 0,
            "count_total": 490
        },
        {
            "area": "瑞穗鄉",
            "cunli": "瑞祥村",
            "house_no": "277",
            "candidates": {
                "1": 167,
                "2": 224,
                "3": 142
            },
            "count_wrong": 19,
            "count_unused": 0,
            "count_total": 876
        },
        {
            "area": "瑞穗鄉",
            "cunli": "瑞北村",
            "house_no": "278",
            "candidates": {
                "1": 145,
                "2": 162,
                "3": 50
            },
            "count_wrong": 4,
            "count_unused": 0,
            "count_total": 552
        },
        {
            "area": "瑞穗鄉",
            "cunli": "舞鶴村",
            "house_no": "279",
            "candidates": {
                "1": 164,
                "2": 303,
                "3": 94
            },
            "count_wrong": 16,
            "count_unused": 0,
            "count_total": 896
        },
        {
            "area": "瑞穗鄉",
            "cunli": "鶴岡村",
            "house_no": "280",
            "candidates": {
                "1": 147,
                "2": 336,
                "3": 85
            },
            "count_wrong": 20,
            "count_unused": 0,
            "count_total": 831
        },
        {
            "area": "瑞穗鄉",
            "cunli": "奇美村",
            "house_no": "281",
            "candidates": {
                "1": 102,
                "2": 64,
                "3": 33
            },
            "count_wrong": 4,
            "count_unused": 0,
            "count_total": 310
        },
        {
            "area": "瑞穗鄉",
            "cunli": "富源村",
            "house_no": "282",
            "candidates": {
                "1": 212,
                "2": 107,
                "3": 90
            },
            "count_wrong": 29,
            "count_unused": 0,
            "count_total": 694
        },
        {
            "area": "瑞穗鄉",
            "cunli": "富民村",
            "house_no": "283",
            "candidates": {
                "1": 158,
                "2": 186,
                "3": 117
            },
            "count_wrong": 41,
            "count_unused": 0,
            "count_total": 794
        },
        {
            "area": "瑞穗鄉",
            "cunli": "富興村",
            "house_no": "284",
            "candidates": {
                "1": 146,
                "2": 132,
                "3": 48
            },
            "count_wrong": 25,
            "count_unused": 0,
            "count_total": 559
        }
    ]
}