{
    "candidates": {
        "1": {
            "name": "榮志強",
            "party": "無"
        }
    },
    "data": [
        {
            "area": "麻豆區",
            "cunli": "晋江里",
            "house_no": "413",
            "candidates": {
                "1": 335
            },
            "count_wrong": 22,
            "count_unused": 0,
            "count_total": 696
        },
        {
            "area": "麻豆區",
            "cunli": "晋江里",
            "house_no": "414",
            "candidates": {
                "1": 365
            },
            "count_wrong": 41,
            "count_unused": 0,
            "count_total": 792
        },
        {
            "area": "麻豆區",
            "cunli": "晋江里",
            "house_no": "415",
            "candidates": {
                "1": 457
            },
            "count_wrong": 52,
            "count_unused": 0,
            "count_total": 865
        }
    ]
}