{
    "candidates": {
        "1": {
            "name": "林哲園",
            "party": "無"
        },
        "2": {
            "name": "呂學琪",
            "party": "中國國民黨"
        }
    },
    "data": [
        {
            "area": "八德區",
            "cunli": "瑞豐里",
            "house_no": "372",
            "candidates": {
                "1": 190,
                "2": 441
            },
            "count_wrong": 24,
            "count_unused": 0,
            "count_total": 989
        },
        {
            "area": "八德區",
            "cunli": "瑞豐里",
            "house_no": "373",
            "candidates": {
                "1": 221,
                "2": 554
            },
            "count_wrong": 33,
            "count_unused": 0,
            "count_total": 1546
        },
        {
            "area": "八德區",
            "cunli": "瑞豐里",
            "house_no": "374",
            "candidates": {
                "1": 146,
                "2": 497
            },
            "count_wrong": 24,
            "count_unused": 0,
            "count_total": 1334
        },
        {
            "area": "八德區",
            "cunli": "瑞豐里",
            "house_no": "375",
            "candidates": {
                "1": 193,
                "2": 281
            },
            "count_wrong": 15,
            "count_unused": 0,
            "count_total": 1025
        }
    ]
}